parquetconv/__init__.py
parquetconv/cli.py
parquetconv-0.2.0.dist-info/METADATA
parquetconv-0.2.0.dist-info/WHEEL
parquetconv-0.2.0.dist-info/entry_points.txt
parquetconv-0.2.0.dist-info/licenses/LICENSE
parquetconv-0.2.0.dist-info/RECORD
