Metadata-Version: 2.4
Name: parquetconv
Version: 0.2.0
Summary: A command-line tool for converting between Parquet and CSV file formats
Project-URL: Homepage, https://github.com/ToyokoLabs/parquetconv
Project-URL: Repository, https://github.com/ToyokoLabs/parquetconv
Project-URL: Issues, https://github.com/ToyokoLabs/parquetconv/issues
Author-email: Sebastian Bassi <sebastian@toyoko.io>
License: MIT
License-File: LICENSE
Keywords: conversion,csv,data,pandas,parquet
Classifier: Development Status :: 4 - Beta
Classifier: Programming Language :: Python :: 3
Classifier: Programming Language :: Python :: 3.9
Classifier: Programming Language :: Python :: 3.10
Classifier: Programming Language :: Python :: 3.11
Classifier: Programming Language :: Python :: 3.12
Classifier: Topic :: Software Development :: Libraries :: Python Modules
Classifier: Topic :: Utilities
Requires-Python: >=3.9
Requires-Dist: hatchling>=1.0.0
Requires-Dist: pandas>=2.3.2
Requires-Dist: pyarrow>=21.0.0
